enshroud/__init__.py
enshroud/enshroud.py
enshroud-1.0.4.dist-info/entry_points.txt
enshroud-1.0.4.dist-info/WHEEL
enshroud-1.0.4.dist-info/METADATA
enshroud-1.0.4.dist-info/RECORD
