Metadata-Version: 2.1
Name: enshroud
Version: 1.0.4
Summary: A steganography tool to hide secret texts in white space.
Home-page: https://github.com/malikakarsh/enShroud.git
Keywords: text steganography,hide text,steganograhy
Author: Akarsh Malik
Author-email: malikakarsh@gmail.com
Requires-Python: >=3.8,<4.0
Classifier: Programming Language :: Python :: 3
Classifier: Programming Language :: Python :: 3.8
Classifier: Programming Language :: Python :: 3.9
Project-URL: Repository, https://github.com/malikakarsh/enShroud.git
